{
  "resourceType": "MedicationRequest",
  "id": "smp-medrx-1-2",
  "text": {
    "status": "generated",
    "div": "<div>Sertraline 25 mg</div>"
  },
  "status": "active",
  "intent": "order",
  "medicationCodeableConcept": {
    "coding": [
      {
        "system": "http://www.nlm.nih.gov/research/umls/rxnorm",
        "code": "312940",
        "display": "Sertraline 25 mg"
      }
    ]
  },
  "subject": {
    "reference": "Patient/patientBSJ1",
    "display": "Betsy Johnson"
  },
  "authoredOn": "2024-06-07",
  "reasonCode": [
    {
      "coding": [
        {
          "system": "http://snomed.info/sct",
          "code": "35489007",
          "display": "Depressive disorder (disorder)"
        }
      ]
    }
  ],
  "dosageInstruction": [
    {
      "sequence": 1,
      "text": "po nightly"
    }
  ]
}