{
  "resourceType": "ServiceRequest",
  "id": "P0723-eLTSS-serviceDiabetesEducation-Initial",
  "meta": {
    "profile": [
      "http://hl7.org/fhir/us/eLTSS/StructureDefinition/ServiceRequest-eltss"
    ]
  },
  "status": "active",
  "intent": "plan",
  "code": {
    "coding": [
      {
        "code": "G0108",
        "system": "urn:oid:2.16.840.1.113883.6.14"
      }
    ],
    "text": "Diabetes outpatient self-management training services, individual, per 30 minutes"
  },
  "quantityRatio": {
    "numerator": {
      "value": 1,
      "unit": "visit"
    },
    "denominator": {
      "value": 1,
      "unit": "week"
    }
  },
  "subject": {
    "reference": "Patient/P0723-patientBSJ1"
  },
  "occurrencePeriod": {
    "start": "2023-06-09",
    "end": "2022-08-01"
  },
  "performer": [
    {
      "reference": "Practitioner/P0723-Practitioner-eLTSS-LisaEducator"
    }
  ],
  "reasonReference": [
    {
      "reference": "Condition/P0723-eLTSS-needDiabetesEducation"
    }
  ],
  "supportingInfo": [
    {
      "reference": "Claim/P0723-eLTSS-claimDiabetesSelfManagement-Initial"
    }
  ]
}
