{
  "resourceType": "ServiceRequest",
  "id": "P0723-mcc-service-edu-ckd",
  "status": "active",
  "intent": "plan",
  "code": {
    "coding": [
      {
        "code": "408982008",
        "system": "http://snomed.info/sct",
        "display": "Renal care education (procedure)"
      }
    ],
    "text": "Education on CKD management"
  },
  "subject": {
    "reference": "Patient/P0723-patientBSJ1"
  },
  "authoredOn": "2023-04-18",
  "requester": {
    "reference": "Practitioner/P0723-Practitioner-jones-vince"
  },
  "performer": [
    {
      "reference": "Practitioner/P0723-Practitioner-smith-julie"
    }
  ],
  "reasonReference": [
    {
      "reference": "Condition/P0723-Prob-CKD"
    }
  ]
}
